<?xml version="1.0" encoding="UTF-8"?>
<objects serializationModel="Studio.01.08.00">
    <object class="AudioFile" id="{4f647664-5957-4515-b881-3815ed53bc51}">
        <property name="assetPath">
            <value>Music/Velvet_Armaments_6.2.1_125BPM.mp3</value>
        </property>
        <property name="isStreaming">
            <value>true</value>
        </property>
        <property name="frequencyInKHz">
            <value>44.0999985</value>
        </property>
        <property name="channelCount">
            <value>2</value>
        </property>
        <property name="length">
            <value>192.05224489795918</value>
        </property>
        <relationship name="masterAssetFolder">
            <destination>{32dc9d01-c288-4fa5-a729-113249d89e4b}</destination>
        </relationship>
    </object>
</objects>
